DataCleaningWithPandas/Setup.py
DataCleaningWithPandas/__init__.py
DataCleaningWithPandas/categorical_encoder.py
DataCleaningWithPandas/data_type_converter.py
DataCleaningWithPandas/date_time_handler.py
DataCleaningWithPandas/missing_value_handler.py
DataCleaningWithPandas/outlier_handler.py
DataCleaningWithPandas/scaler.py
DataCleaningWithPandas/text_cleaner.py
DataCleaningWithPandas-0.1.9.dist-info/METADATA
DataCleaningWithPandas-0.1.9.dist-info/WHEEL
DataCleaningWithPandas-0.1.9.dist-info/top_level.txt
DataCleaningWithPandas-0.1.9.dist-info/RECORD
